suofei_scale/__init__.py
suofei_scale/app.py
suofei_scale-0.0.1.dist-info/METADATA
suofei_scale-0.0.1.dist-info/WHEEL
suofei_scale-0.0.1.dist-info/RECORD
