Metadata-Version: 2.1
Name: suofei-scale
Version: 0.0.1
Summary: SUOFEI POSTAL SCALE DRIVER
Author: AFraczkowski
Requires-Python: >=3.8,<4.0
Classifier: Programming Language :: Python :: 3
Classifier: Programming Language :: Python :: 3.8
Classifier: Programming Language :: Python :: 3.9
Classifier: Programming Language :: Python :: 3.10
Classifier: Programming Language :: Python :: 3.11
Classifier: Programming Language :: Python :: 3.12
Requires-Dist: maho-mqtt (==2.1.0)
Requires-Dist: pyserial (==3.5)
